mdninja/__init__.py
mdninja/templates/default.html
mdninja-1.0.3.dist-info/METADATA
mdninja-1.0.3.dist-info/WHEEL
mdninja-1.0.3.dist-info/entry_points.txt
mdninja-1.0.3.dist-info/top_level.txt
mdninja-1.0.3.dist-info/RECORD
