Metadata-Version: 2.1
Name: mdninja
Version: 1.0.3
Summary: mdninja + markdown + jinja2 = beautiful HTML
Home-page: https://github.com/btbytes/mdninja
Author: Pradeep Gowda
Author-email: btbytes+mdninja@gmail.com
License: MIT
Keywords: markdown jinja2 publishing
Classifier: Development Status :: 4 - Beta
Classifier: Intended Audience :: End Users/Desktop
Classifier: Topic :: Utilities
Classifier: License :: OSI Approved :: MIT License
Classifier: Programming Language :: Python :: 3
Classifier: Programming Language :: Python :: 3.9
Classifier: Programming Language :: Python :: 3.10
Classifier: Programming Language :: Python :: 3.11
Requires-Python: ~=3.9
Requires-Dist: markdown
Requires-Dist: jinja2
Requires-Dist: click
